{
  "version": "4.0.0",
  "id": "converted-diagram-1778241725872",
  "title": "",
  "type": "ClassDiagram",
  "nodes": [
    {
      "id": "ff2a298c-cd09-447f-b868-72d4aa1d34dc",
      "type": "class",
      "position": {
        "x": -780,
        "y": -180
      },
      "width": 180,
      "height": 130,
      "measured": {
        "width": 180,
        "height": 130
      },
      "data": {
        "name": "Tag",
        "methods": [],
        "attributes": [
          {
            "id": "7c13914f-6268-4ed8-945d-20d33769e795",
            "name": "name",
            "visibility": "public",
            "attributeType": "str",
            "code": "",
            "implementationType": "none",
            "isOptional": false
          },
          {
            "id": "9ea3d4de-80e3-4ae5-b5f7-2a70d17ed8fe",
            "name": "color",
            "visibility": "public",
            "attributeType": "str",
            "code": "",
            "implementationType": "none",
            "isOptional": false,
            "defaultValue": "#3B82F6"
          },
          {
            "id": "1451cd61-6d45-478c-9047-085ee7e871e9",
            "name": "id",
            "visibility": "public",
            "attributeType": "int",
            "code": "",
            "implementationType": "none",
            "isOptional": false
          }
        ]
      }
    },
    {
      "id": "53490d70-1ecb-4595-89f0-a2309285454e",
      "type": "class",
      "position": {
        "x": 110,
        "y": -590
      },
      "width": 250,
      "height": 250,
      "measured": {
        "width": 250,
        "height": 250
      },
      "data": {
        "name": "Interaction",
        "methods": [],
        "attributes": [
          {
            "id": "ba649c7e-a8b4-4668-a2c0-5adcd3039340",
            "name": "created_at",
            "visibility": "public",
            "attributeType": "datetime",
            "code": "",
            "implementationType": "none",
            "isOptional": false
          },
          {
            "id": "ee6d44d7-9825-4da0-ad55-a26ac83c3fac",
            "name": "subject",
            "visibility": "public",
            "attributeType": "str",
            "code": "",
            "implementationType": "none",
            "isOptional": true
          },
          {
            "id": "db194d8e-396b-4067-aefa-dc7c12e0acf2",
            "name": "type",
            "visibility": "public",
            "attributeType": "InteractionType",
            "code": "",
            "implementationType": "none",
            "isOptional": false
          },
          {
            "id": "30251a57-d26d-4a29-b683-d0e6c8e038f2",
            "name": "content",
            "visibility": "public",
            "attributeType": "str",
            "code": "",
            "implementationType": "none",
            "isOptional": false
          },
          {
            "id": "cd2f2b81-7e0c-4a5e-a826-47b5a3a65a5b",
            "name": "occurred_at",
            "visibility": "public",
            "attributeType": "datetime",
            "code": "",
            "implementationType": "none",
            "isOptional": false
          },
          {
            "id": "7dfbc971-ede4-48fa-add1-453c78e02748",
            "name": "id",
            "visibility": "public",
            "attributeType": "int",
            "code": "",
            "implementationType": "none",
            "isOptional": false
          },
          {
            "id": "b422bed6-92e3-498e-8de4-110d9d7dd9f5",
            "name": "direction",
            "visibility": "public",
            "attributeType": "InteractionDirection",
            "code": "",
            "implementationType": "none",
            "isOptional": true
          }
        ]
      }
    },
    {
      "id": "e1022906-3e3c-448b-a5bf-c30f39a981ad",
      "type": "class",
      "position": {
        "x": -630,
        "y": -830
      },
      "width": 160,
      "height": 260,
      "measured": {
        "width": 160,
        "height": 260
      },
      "data": {
        "name": "Industry",
        "methods": [],
        "attributes": [
          {
            "id": "62b8b270-503a-470d-abe4-2dc502ddb7f6",
            "name": "MANUFACTURING",
            "visibility": "public",
            "attributeType": "str",
            "code": "",
            "implementationType": "none",
            "isOptional": false
          },
          {
            "id": "33bd1049-5e8e-47e2-9531-28cfe981edf4",
            "name": "HEALTHCARE",
            "visibility": "public",
            "attributeType": "str",
            "code": "",
            "implementationType": "none",
            "isOptional": false
          },
          {
            "id": "480a789c-8003-4ed5-b523-b0903e2eb6e0",
            "name": "FINANCE",
            "visibility": "public",
            "attributeType": "str",
            "code": "",
            "implementationType": "none",
            "isOptional": false
          },
          {
            "id": "bc64be16-60ec-4a8c-8aea-11640ac51300",
            "name": "OTHER",
            "visibility": "public",
            "attributeType": "str",
            "code": "",
            "implementationType": "none",
            "isOptional": false
          },
          {
            "id": "30495c31-a814-45f0-ba7a-c8a33bede839",
            "name": "TECHNOLOGY",
            "visibility": "public",
            "attributeType": "str",
            "code": "",
            "implementationType": "none",
            "isOptional": false
          },
          {
            "id": "f04af97b-3e22-459d-9402-408e3eca145f",
            "name": "SERVICES",
            "visibility": "public",
            "attributeType": "str",
            "code": "",
            "implementationType": "none",
            "isOptional": false
          },
          {
            "id": "ab881589-309d-4f88-93e6-9a4aa9bb5538",
            "name": "RETAIL",
            "visibility": "public",
            "attributeType": "str",
            "code": "",
            "implementationType": "none",
            "isOptional": false
          }
        ],
        "stereotype": "Enumeration"
      }
    },
    {
      "id": "226f6331-6731-4369-acf3-3d600da14d97",
      "type": "class",
      "position": {
        "x": -450,
        "y": -820
      },
      "width": 160,
      "height": 170,
      "measured": {
        "width": 160,
        "height": 170
      },
      "data": {
        "name": "InteractionType",
        "methods": [],
        "attributes": [
          {
            "id": "3c382335-f301-4bf5-9cf2-66f3d5b4ab6f",
            "name": "MEETING",
            "visibility": "public",
            "attributeType": "str",
            "code": "",
            "implementationType": "none",
            "isOptional": false
          },
          {
            "id": "071260fa-d30b-4a27-be28-7d8789370e2a",
            "name": "EMAIL",
            "visibility": "public",
            "attributeType": "str",
            "code": "",
            "implementationType": "none",
            "isOptional": false
          },
          {
            "id": "70de196d-8310-4131-9bd5-44675f8d5da8",
            "name": "CALL",
            "visibility": "public",
            "attributeType": "str",
            "code": "",
            "implementationType": "none",
            "isOptional": false
          },
          {
            "id": "49ec4063-6b5a-45d3-9935-6c69c479239a",
            "name": "NOTE",
            "visibility": "public",
            "attributeType": "str",
            "code": "",
            "implementationType": "none",
            "isOptional": false
          }
        ],
        "stereotype": "Enumeration"
      }
    },
    {
      "id": "00c036a4-454e-4449-9a9b-6b3f03969d49",
      "type": "class",
      "position": {
        "x": -390,
        "y": 430
      },
      "width": 340,
      "height": 340,
      "measured": {
        "width": 340,
        "height": 340
      },
      "data": {
        "name": "Opportunity",
        "methods": [],
        "attributes": [
          {
            "id": "5ccc2680-ffb6-43f1-bd61-21281ae87e95",
            "name": "expected_close_date",
            "visibility": "public",
            "attributeType": "date",
            "code": "",
            "implementationType": "none",
            "isOptional": true
          },
          {
            "id": "0915c85a-66dc-4299-bc29-b253012b85ee",
            "name": "id",
            "visibility": "public",
            "attributeType": "int",
            "code": "",
            "implementationType": "none",
            "isOptional": false
          },
          {
            "id": "16db3e70-da43-4d47-98ce-ecc3cacb0d32",
            "name": "probability",
            "visibility": "public",
            "attributeType": "int",
            "code": "",
            "implementationType": "none",
            "isOptional": true
          },
          {
            "id": "21af13ce-7124-4e6a-8fdf-ae938993fa4e",
            "name": "value",
            "visibility": "public",
            "attributeType": "float",
            "code": "",
            "implementationType": "none",
            "isOptional": true
          },
          {
            "id": "1d7f1d05-bc2b-48c9-9938-9003684db0ec",
            "name": "closed_at",
            "visibility": "public",
            "attributeType": "datetime",
            "code": "",
            "implementationType": "none",
            "isOptional": true
          },
          {
            "id": "2a846d8d-75ef-4d44-95a8-1eb013d3f690",
            "name": "stage",
            "visibility": "public",
            "attributeType": "OpportunityStage",
            "code": "",
            "implementationType": "none",
            "isOptional": false,
            "defaultValue": "PROSPECTING"
          },
          {
            "id": "0337f90a-c308-4ba7-b0db-800693e4df09",
            "name": "updated_at",
            "visibility": "public",
            "attributeType": "datetime",
            "code": "",
            "implementationType": "none",
            "isOptional": false
          },
          {
            "id": "f6e5eaf7-78f9-40ed-9660-aa130e9b7d59",
            "name": "description",
            "visibility": "public",
            "attributeType": "str",
            "code": "",
            "implementationType": "none",
            "isOptional": true
          },
          {
            "id": "31d4a401-1c78-42e6-bde0-2fb7c3938ea2",
            "name": "created_at",
            "visibility": "public",
            "attributeType": "datetime",
            "code": "",
            "implementationType": "none",
            "isOptional": false
          },
          {
            "id": "78b80945-3a02-4e55-96a8-09cf31bf33f4",
            "name": "title",
            "visibility": "public",
            "attributeType": "str",
            "code": "",
            "implementationType": "none",
            "isOptional": false
          }
        ]
      }
    },
    {
      "id": "aaddf56f-d3cb-4eab-8223-f08b85c10f1f",
      "type": "class",
      "position": {
        "x": -270,
        "y": -330
      },
      "width": 340,
      "height": 460,
      "measured": {
        "width": 340,
        "height": 460
      },
      "data": {
        "name": "Contact",
        "methods": [],
        "attributes": [
          {
            "id": "9065f64f-e3b6-4c76-95b4-0a8b9aa3c720",
            "name": "updated_at",
            "visibility": "public",
            "attributeType": "datetime",
            "code": "",
            "implementationType": "none",
            "isOptional": false
          },
          {
            "id": "8cf8da1e-73ca-4149-99d6-37056420bc90",
            "name": "phone",
            "visibility": "public",
            "attributeType": "str",
            "code": "",
            "implementationType": "none",
            "isOptional": true
          },
          {
            "id": "9f545822-14bf-42d3-bd34-64ca46a728e2",
            "name": "lead_score_level",
            "visibility": "public",
            "attributeType": "LeadScoreLevel",
            "code": "",
            "implementationType": "none",
            "isOptional": false,
            "defaultValue": "COLD"
          },
          {
            "id": "1129f147-b809-4871-a2a6-36d820fe048c",
            "name": "email",
            "visibility": "public",
            "attributeType": "str",
            "code": "",
            "implementationType": "none",
            "isOptional": true
          },
          {
            "id": "fe981546-ccd8-4b2b-892e-6e27367fbab4",
            "name": "lead_score",
            "visibility": "public",
            "attributeType": "int",
            "code": "",
            "implementationType": "none",
            "isOptional": false,
            "defaultValue": 0
          },
          {
            "id": "4a14d1b3-50bc-44cb-978d-aa0dc2ebdafb",
            "name": "last_name",
            "visibility": "public",
            "attributeType": "str",
            "code": "",
            "implementationType": "none",
            "isOptional": false
          },
          {
            "id": "86f26f9f-8d69-44b7-8cd3-f8980417f1fb",
            "name": "profile_picture_url",
            "visibility": "public",
            "attributeType": "str",
            "code": "",
            "implementationType": "none",
            "isOptional": true
          },
          {
            "id": "cdc991ad-bf4d-4642-964e-ac1661c64ebc",
            "name": "first_name",
            "visibility": "public",
            "attributeType": "str",
            "code": "",
            "implementationType": "none",
            "isOptional": false
          },
          {
            "id": "d7c69aec-5673-4eba-b1a3-eb1a6b2fd7e9",
            "name": "created_at",
            "visibility": "public",
            "attributeType": "datetime",
            "code": "",
            "implementationType": "none",
            "isOptional": false
          },
          {
            "id": "bcf7cf7b-1038-4ee5-ac37-73089d19a930",
            "name": "linkedin_url",
            "visibility": "public",
            "attributeType": "str",
            "code": "",
            "implementationType": "none",
            "isOptional": true
          },
          {
            "id": "be18db5b-bfef-4204-9cf7-d8822fcece89",
            "name": "id",
            "visibility": "public",
            "attributeType": "int",
            "code": "",
            "implementationType": "none",
            "isOptional": false
          },
          {
            "id": "915baf6b-16e4-4210-86c6-3b5a49a26ca1",
            "name": "notes",
            "visibility": "public",
            "attributeType": "str",
            "code": "",
            "implementationType": "none",
            "isOptional": true
          },
          {
            "id": "e3a02d6c-2c9d-43f8-a636-6f39fc07704b",
            "name": "job_title",
            "visibility": "public",
            "attributeType": "str",
            "code": "",
            "implementationType": "none",
            "isOptional": true
          },
          {
            "id": "2c34c4e0-1568-4348-b1d9-7379d79ffcd3",
            "name": "is_enriched",
            "visibility": "public",
            "attributeType": "bool",
            "code": "",
            "implementationType": "none",
            "isOptional": false,
            "defaultValue": false
          }
        ]
      }
    },
    {
      "id": "ec988dfa-a549-477d-b8ef-66282b08817f",
      "type": "class",
      "position": {
        "x": -260,
        "y": -830
      },
      "width": 160,
      "height": 140,
      "measured": {
        "width": 160,
        "height": 140
      },
      "data": {
        "name": "LeadScoreLevel",
        "methods": [],
        "attributes": [
          {
            "id": "a8f22db2-0938-40b9-ad21-793ad07b841b",
            "name": "COLD",
            "visibility": "public",
            "attributeType": "str",
            "code": "",
            "implementationType": "none",
            "isOptional": false
          },
          {
            "id": "4cea14b8-f80b-4bb0-9593-2d104c442573",
            "name": "WARM",
            "visibility": "public",
            "attributeType": "str",
            "code": "",
            "implementationType": "none",
            "isOptional": false
          },
          {
            "id": "fe282a6d-6d93-4e4d-9bc6-7e5c94a11204",
            "name": "HOT",
            "visibility": "public",
            "attributeType": "str",
            "code": "",
            "implementationType": "none",
            "isOptional": false
          }
        ],
        "stereotype": "Enumeration"
      }
    },
    {
      "id": "9b3c4c9c-64b0-4937-98e5-bdddb729b882",
      "type": "class",
      "position": {
        "x": -770,
        "y": 80
      },
      "width": 180,
      "height": 430,
      "measured": {
        "width": 180,
        "height": 430
      },
      "data": {
        "name": "Company",
        "methods": [],
        "attributes": [
          {
            "id": "8c3d9e2a-58f1-418e-8f0d-ad6160947282",
            "name": "website",
            "visibility": "public",
            "attributeType": "str",
            "code": "",
            "implementationType": "none",
            "isOptional": true
          },
          {
            "id": "d4b1fe2e-e058-4823-b5fd-3d4832a08430",
            "name": "phone",
            "visibility": "public",
            "attributeType": "str",
            "code": "",
            "implementationType": "none",
            "isOptional": true
          },
          {
            "id": "e2f3945d-35e5-4ddc-b2f2-86c948fdb44d",
            "name": "name",
            "visibility": "public",
            "attributeType": "str",
            "code": "",
            "implementationType": "none",
            "isOptional": false
          },
          {
            "id": "296514fd-100a-4bb1-8fa9-30f364e1d3ce",
            "name": "created_at",
            "visibility": "public",
            "attributeType": "datetime",
            "code": "",
            "implementationType": "none",
            "isOptional": false
          },
          {
            "id": "b391e3c6-e1e6-4766-917d-c2e822b5e0f1",
            "name": "linkedin_url",
            "visibility": "public",
            "attributeType": "str",
            "code": "",
            "implementationType": "none",
            "isOptional": true
          },
          {
            "id": "afda279f-5336-4805-9e17-33ad5e3e2303",
            "name": "description",
            "visibility": "public",
            "attributeType": "str",
            "code": "",
            "implementationType": "none",
            "isOptional": true
          },
          {
            "id": "de8b940c-febe-4aac-8462-49456b200ee1",
            "name": "updated_at",
            "visibility": "public",
            "attributeType": "datetime",
            "code": "",
            "implementationType": "none",
            "isOptional": false
          },
          {
            "id": "a73f174c-759a-4312-b1ba-50255801eef3",
            "name": "id",
            "visibility": "public",
            "attributeType": "int",
            "code": "",
            "implementationType": "none",
            "isOptional": false
          },
          {
            "id": "b828b051-dc59-4f8d-bf00-8b71d5cfa623",
            "name": "country",
            "visibility": "public",
            "attributeType": "str",
            "code": "",
            "implementationType": "none",
            "isOptional": true
          },
          {
            "id": "0428a747-c3d4-46dd-9f6a-72a9891cf958",
            "name": "size",
            "visibility": "public",
            "attributeType": "CompanySize",
            "code": "",
            "implementationType": "none",
            "isOptional": true
          },
          {
            "id": "fc1db470-b326-4d60-bad6-d225ce5f8cb3",
            "name": "city",
            "visibility": "public",
            "attributeType": "str",
            "code": "",
            "implementationType": "none",
            "isOptional": true
          },
          {
            "id": "27b53eb5-4027-4099-87f0-e3869b7ec05b",
            "name": "industry",
            "visibility": "public",
            "attributeType": "Industry",
            "code": "",
            "implementationType": "none",
            "isOptional": false
          },
          {
            "id": "206b6ff2-b91b-4983-b853-a33ae4e6b07d",
            "name": "address",
            "visibility": "public",
            "attributeType": "str",
            "code": "",
            "implementationType": "none",
            "isOptional": true
          }
        ]
      }
    },
    {
      "id": "278327b9-3f33-4fcc-aa98-c144c0933a65",
      "type": "class",
      "position": {
        "x": 400,
        "y": 190
      },
      "width": 180,
      "height": 310,
      "measured": {
        "width": 180,
        "height": 310
      },
      "data": {
        "name": "User",
        "methods": [],
        "attributes": [
          {
            "id": "b0534f49-b018-412c-b013-25a67385bc4c",
            "name": "last_name",
            "visibility": "public",
            "attributeType": "str",
            "code": "",
            "implementationType": "none",
            "isOptional": false
          },
          {
            "id": "eaa57325-a4b8-4436-bdae-d98dcb30d5a8",
            "name": "first_name",
            "visibility": "public",
            "attributeType": "str",
            "code": "",
            "implementationType": "none",
            "isOptional": false
          },
          {
            "id": "19a657fe-9d9c-4e54-b9f4-e863fb6e6535",
            "name": "password_hash",
            "visibility": "public",
            "attributeType": "str",
            "code": "",
            "implementationType": "none",
            "isOptional": false
          },
          {
            "id": "08537d8e-6371-4fae-ac32-e1452cb81dba",
            "name": "last_login",
            "visibility": "public",
            "attributeType": "datetime",
            "code": "",
            "implementationType": "none",
            "isOptional": true
          },
          {
            "id": "9d5efdd6-8315-43e4-89d4-09f0cda4119d",
            "name": "email",
            "visibility": "public",
            "attributeType": "str",
            "code": "",
            "implementationType": "none",
            "isOptional": false
          },
          {
            "id": "e9ff5407-6bcf-4ca0-984d-2118cca10839",
            "name": "is_active",
            "visibility": "public",
            "attributeType": "bool",
            "code": "",
            "implementationType": "none",
            "isOptional": false,
            "defaultValue": true
          },
          {
            "id": "3ba28147-4bcd-4c1d-9917-c47f33ac6b5d",
            "name": "created_at",
            "visibility": "public",
            "attributeType": "datetime",
            "code": "",
            "implementationType": "none",
            "isOptional": false
          },
          {
            "id": "b959694a-6ac9-4781-b81e-7950357f807b",
            "name": "id",
            "visibility": "public",
            "attributeType": "int",
            "code": "",
            "implementationType": "none",
            "isOptional": false
          },
          {
            "id": "ec1cb571-8994-4b9d-99b3-314c55f8492b",
            "name": "role",
            "visibility": "public",
            "attributeType": "UserRole",
            "code": "",
            "implementationType": "none",
            "isOptional": false
          }
        ]
      }
    },
    {
      "id": "e2ffed0e-86e2-4ef9-bb83-c7d2f87175a9",
      "type": "class",
      "position": {
        "x": -790,
        "y": -430
      },
      "width": 200,
      "height": 190,
      "measured": {
        "width": 200,
        "height": 190
      },
      "data": {
        "name": "ScoreHistory",
        "methods": [],
        "attributes": [
          {
            "id": "0a2485d1-48cc-4cc6-82e1-6683150cc0e3",
            "name": "id",
            "visibility": "public",
            "attributeType": "int",
            "code": "",
            "implementationType": "none",
            "isOptional": false
          },
          {
            "id": "ccb2e2e8-625e-4a70-9276-d3d1790d63c7",
            "name": "calculated_at",
            "visibility": "public",
            "attributeType": "datetime",
            "code": "",
            "implementationType": "none",
            "isOptional": false
          },
          {
            "id": "b3157cd1-b05e-416e-8e09-57d606aa98fa",
            "name": "reason",
            "visibility": "public",
            "attributeType": "str",
            "code": "",
            "implementationType": "none",
            "isOptional": false
          },
          {
            "id": "5295a893-3b37-4390-a670-5facad4cd3a2",
            "name": "new_score",
            "visibility": "public",
            "attributeType": "int",
            "code": "",
            "implementationType": "none",
            "isOptional": false
          },
          {
            "id": "8a56edad-2a22-4c9e-84cc-a70e0b36968b",
            "name": "old_score",
            "visibility": "public",
            "attributeType": "int",
            "code": "",
            "implementationType": "none",
            "isOptional": false
          }
        ]
      }
    },
    {
      "id": "5c23416e-3e81-4e62-a9f8-9702566b5f49",
      "type": "class",
      "position": {
        "x": 350,
        "y": -810
      },
      "width": 160,
      "height": 200,
      "measured": {
        "width": 160,
        "height": 200
      },
      "data": {
        "name": "CompanySize",
        "methods": [],
        "attributes": [
          {
            "id": "b8fbcc63-c7bd-4265-8ca0-82a064b1ea7c",
            "name": "STARTUP",
            "visibility": "public",
            "attributeType": "str",
            "code": "",
            "implementationType": "none",
            "isOptional": false
          },
          {
            "id": "efc4376c-7d0d-45e7-9b80-e9b587e52ad0",
            "name": "ENTERPRISE",
            "visibility": "public",
            "attributeType": "str",
            "code": "",
            "implementationType": "none",
            "isOptional": false
          },
          {
            "id": "305e727d-1a9f-4dc6-8a3f-b898fb896d50",
            "name": "LARGE",
            "visibility": "public",
            "attributeType": "str",
            "code": "",
            "implementationType": "none",
            "isOptional": false
          },
          {
            "id": "057b1863-3a4f-45bc-b169-a52980212b3c",
            "name": "MEDIUM",
            "visibility": "public",
            "attributeType": "str",
            "code": "",
            "implementationType": "none",
            "isOptional": false
          },
          {
            "id": "d8c2a18e-6006-4732-9318-8e4c59ad2afe",
            "name": "SMALL",
            "visibility": "public",
            "attributeType": "str",
            "code": "",
            "implementationType": "none",
            "isOptional": false
          }
        ],
        "stereotype": "Enumeration"
      }
    },
    {
      "id": "ef128c67-c532-4b67-b248-732b587445a7",
      "type": "class",
      "position": {
        "x": 270,
        "y": -280
      },
      "width": 190,
      "height": 190,
      "measured": {
        "width": 190,
        "height": 190
      },
      "data": {
        "name": "EnrichmentLog",
        "methods": [],
        "attributes": [
          {
            "id": "9de45cda-b4df-4245-9ec6-483303f2a430",
            "name": "id",
            "visibility": "public",
            "attributeType": "int",
            "code": "",
            "implementationType": "none",
            "isOptional": false
          },
          {
            "id": "844169b5-1dce-43e9-b755-eac6a46b572f",
            "name": "error_message",
            "visibility": "public",
            "attributeType": "str",
            "code": "",
            "implementationType": "none",
            "isOptional": true
          },
          {
            "id": "a4da4875-85f6-4547-b607-bd7061769b51",
            "name": "is_successful",
            "visibility": "public",
            "attributeType": "bool",
            "code": "",
            "implementationType": "none",
            "isOptional": false
          },
          {
            "id": "5ee9693a-b72c-4157-a006-4854d18e976d",
            "name": "linkedin_url",
            "visibility": "public",
            "attributeType": "str",
            "code": "",
            "implementationType": "none",
            "isOptional": false
          },
          {
            "id": "41e3b09f-caca-45ce-9ce6-6f233771eeee",
            "name": "enriched_at",
            "visibility": "public",
            "attributeType": "datetime",
            "code": "",
            "implementationType": "none",
            "isOptional": false
          }
        ]
      }
    },
    {
      "id": "9b5bec19-9213-42b3-8fc1-780a02dc0912",
      "type": "class",
      "position": {
        "x": -60,
        "y": -820
      },
      "width": 160,
      "height": 230,
      "measured": {
        "width": 160,
        "height": 230
      },
      "data": {
        "name": "OpportunityStage",
        "methods": [],
        "attributes": [
          {
            "id": "206cbb41-b615-4b98-80a8-25bcbf4ea519",
            "name": "PROPOSAL",
            "visibility": "public",
            "attributeType": "str",
            "code": "",
            "implementationType": "none",
            "isOptional": false
          },
          {
            "id": "1db6afdb-92e5-4889-a926-091ba57f5d25",
            "name": "QUALIFICATION",
            "visibility": "public",
            "attributeType": "str",
            "code": "",
            "implementationType": "none",
            "isOptional": false
          },
          {
            "id": "33b4b5bf-b915-454b-97bf-3ef7555311d9",
            "name": "CLOSED_LOST",
            "visibility": "public",
            "attributeType": "str",
            "code": "",
            "implementationType": "none",
            "isOptional": false
          },
          {
            "id": "5f7c2fea-18a9-467b-ab6d-1d0741de65d6",
            "name": "PROSPECTING",
            "visibility": "public",
            "attributeType": "str",
            "code": "",
            "implementationType": "none",
            "isOptional": false
          },
          {
            "id": "a74d27b1-5ba9-4f01-8445-504f6c0e4179",
            "name": "CLOSED_WON",
            "visibility": "public",
            "attributeType": "str",
            "code": "",
            "implementationType": "none",
            "isOptional": false
          },
          {
            "id": "b291531f-c847-43de-a08c-934ccb0fbfc2",
            "name": "NEGOTIATION",
            "visibility": "public",
            "attributeType": "str",
            "code": "",
            "implementationType": "none",
            "isOptional": false
          }
        ],
        "stereotype": "Enumeration"
      }
    },
    {
      "id": "393555d5-0f26-4dd8-a594-617199518fd0",
      "type": "class",
      "position": {
        "x": -260,
        "y": -670
      },
      "width": 160,
      "height": 140,
      "measured": {
        "width": 160,
        "height": 140
      },
      "data": {
        "name": "UserRole",
        "methods": [],
        "attributes": [
          {
            "id": "14edf468-8f98-470b-9e58-7b5e98826055",
            "name": "SALES_MANAGER",
            "visibility": "public",
            "attributeType": "str",
            "code": "",
            "implementationType": "none",
            "isOptional": false
          },
          {
            "id": "d596bce3-5bff-47c3-b77e-78c42b1aef5e",
            "name": "ADMIN",
            "visibility": "public",
            "attributeType": "str",
            "code": "",
            "implementationType": "none",
            "isOptional": false
          },
          {
            "id": "6508afba-01b1-4a88-bf90-17e09fae41f3",
            "name": "SALES_REP",
            "visibility": "public",
            "attributeType": "str",
            "code": "",
            "implementationType": "none",
            "isOptional": false
          }
        ],
        "stereotype": "Enumeration"
      }
    },
    {
      "id": "72d64804-891c-438b-bfed-6ecee0bfd085",
      "type": "class",
      "position": {
        "x": 640,
        "y": -150
      },
      "width": 180,
      "height": 220,
      "measured": {
        "width": 180,
        "height": 220
      },
      "data": {
        "name": "GeneratedEmail",
        "methods": [],
        "attributes": [
          {
            "id": "462345e8-6aca-425a-abd5-421942a26c32",
            "name": "created_at",
            "visibility": "public",
            "attributeType": "datetime",
            "code": "",
            "implementationType": "none",
            "isOptional": false
          },
          {
            "id": "6362726d-1389-47f9-ae51-e825932cf657",
            "name": "sent_at",
            "visibility": "public",
            "attributeType": "datetime",
            "code": "",
            "implementationType": "none",
            "isOptional": true
          },
          {
            "id": "a9862d66-c2d9-4413-ba67-eb69acbeb842",
            "name": "is_sent",
            "visibility": "public",
            "attributeType": "bool",
            "code": "",
            "implementationType": "none",
            "isOptional": false,
            "defaultValue": false
          },
          {
            "id": "3d270b20-1c88-468a-8c00-a3bf953d8973",
            "name": "body",
            "visibility": "public",
            "attributeType": "str",
            "code": "",
            "implementationType": "none",
            "isOptional": false
          },
          {
            "id": "7387545b-0833-4fa6-a171-68bcaead6ef7",
            "name": "subject",
            "visibility": "public",
            "attributeType": "str",
            "code": "",
            "implementationType": "none",
            "isOptional": false
          },
          {
            "id": "11dcb6d3-03ad-4a31-bae8-b720007d2f68",
            "name": "id",
            "visibility": "public",
            "attributeType": "int",
            "code": "",
            "implementationType": "none",
            "isOptional": false
          }
        ]
      }
    },
    {
      "id": "2d584aa6-7ca2-4d21-8510-57f70750bfb4",
      "type": "class",
      "position": {
        "x": 810,
        "y": 290
      },
      "width": 180,
      "height": 220,
      "measured": {
        "width": 180,
        "height": 220
      },
      "data": {
        "name": "EmailTemplate",
        "methods": [],
        "attributes": [
          {
            "id": "3130824c-af35-4530-842a-42c16d95ad24",
            "name": "created_at",
            "visibility": "public",
            "attributeType": "datetime",
            "code": "",
            "implementationType": "none",
            "isOptional": false
          },
          {
            "id": "8eebb9c7-9b5d-469c-9933-86613023176d",
            "name": "category",
            "visibility": "public",
            "attributeType": "str",
            "code": "",
            "implementationType": "none",
            "isOptional": false
          },
          {
            "id": "9e30b3b0-45e7-470a-a759-107261364ca4",
            "name": "body_template",
            "visibility": "public",
            "attributeType": "str",
            "code": "",
            "implementationType": "none",
            "isOptional": false
          },
          {
            "id": "f9b723e9-a58a-4266-bb2f-a782eb802d77",
            "name": "subject_template",
            "visibility": "public",
            "attributeType": "str",
            "code": "",
            "implementationType": "none",
            "isOptional": false
          },
          {
            "id": "62e356b2-02b2-42bd-b9ed-d58783aebb12",
            "name": "id",
            "visibility": "public",
            "attributeType": "int",
            "code": "",
            "implementationType": "none",
            "isOptional": false
          },
          {
            "id": "ed9dfb42-0d46-4a77-9248-937918a26e50",
            "name": "name",
            "visibility": "public",
            "attributeType": "str",
            "code": "",
            "implementationType": "none",
            "isOptional": false
          }
        ]
      }
    },
    {
      "id": "c24f8043-a8d8-4caa-b6ff-c4df741bc4fc",
      "type": "class",
      "position": {
        "x": 140,
        "y": -810
      },
      "width": 170,
      "height": 110,
      "measured": {
        "width": 170,
        "height": 110
      },
      "data": {
        "name": "InteractionDirection",
        "methods": [],
        "attributes": [
          {
            "id": "1dc3970a-0f3d-4af9-b19b-546f57565230",
            "name": "INBOUND",
            "visibility": "public",
            "attributeType": "str",
            "code": "",
            "implementationType": "none",
            "isOptional": false
          },
          {
            "id": "52a11e97-06ae-476e-895c-425145812394",
            "name": "OUTBOUND",
            "visibility": "public",
            "attributeType": "str",
            "code": "",
            "implementationType": "none",
            "isOptional": false
          }
        ],
        "stereotype": "Enumeration"
      }
    },
    {
      "id": "fb02ddde-ec4d-4181-bc34-7cabad68eca1",
      "type": "class",
      "position": {
        "x": 90,
        "y": 540
      },
      "width": 220,
      "height": 250,
      "measured": {
        "width": 220,
        "height": 250
      },
      "data": {
        "name": "Task",
        "methods": [],
        "attributes": [
          {
            "id": "f7f5c06c-9bd8-4327-aad1-b642f428edce",
            "name": "description",
            "visibility": "public",
            "attributeType": "str",
            "code": "",
            "implementationType": "none",
            "isOptional": true
          },
          {
            "id": "9d8c5967-e3b0-4e8d-a1da-dceb7b3bfea4",
            "name": "due_date",
            "visibility": "public",
            "attributeType": "datetime",
            "code": "",
            "implementationType": "none",
            "isOptional": true
          },
          {
            "id": "5e91b085-c45d-4a13-8449-94e33244b831",
            "name": "created_at",
            "visibility": "public",
            "attributeType": "datetime",
            "code": "",
            "implementationType": "none",
            "isOptional": false
          },
          {
            "id": "96118621-2b99-402f-8e5b-e6850527028e",
            "name": "title",
            "visibility": "public",
            "attributeType": "str",
            "code": "",
            "implementationType": "none",
            "isOptional": false
          },
          {
            "id": "ab1271f8-3925-42dd-8b88-eb2d91bbfe1e",
            "name": "id",
            "visibility": "public",
            "attributeType": "int",
            "code": "",
            "implementationType": "none",
            "isOptional": false
          },
          {
            "id": "b713c507-bf5f-4095-aa47-5a7b88358d82",
            "name": "completed_at",
            "visibility": "public",
            "attributeType": "datetime",
            "code": "",
            "implementationType": "none",
            "isOptional": true
          },
          {
            "id": "bcf849ab-67f8-4eb0-a970-5b3285d70cd0",
            "name": "is_completed",
            "visibility": "public",
            "attributeType": "bool",
            "code": "",
            "implementationType": "none",
            "isOptional": false,
            "defaultValue": false
          }
        ]
      }
    }
  ],
  "edges": [
    {
      "id": "8ab8b6fb-33e5-48eb-99d0-190d5dc5d392",
      "source": "2d584aa6-7ca2-4d21-8510-57f70750bfb4",
      "target": "278327b9-3f33-4fcc-aa98-c144c0933a65",
      "type": "ClassBidirectional",
      "sourceHandle": "left-top",
      "targetHandle": "right-bottom",
      "data": {
        "label": "template_user",
        "name": "template_user",
        "sourceMultiplicity": "0..*",
        "targetMultiplicity": "1..1",
        "sourceRole": "email_templates",
        "targetRole": "created_by",
        "isManuallyLayouted": false,
        "messages": [],
        "points": [
          {
            "x": 810,
            "y": 395
          },
          {
            "x": 580,
            "y": 395
          }
        ]
      }
    },
    {
      "id": "afc4661c-8768-4609-89b4-91e7028d4892",
      "source": "aaddf56f-d3cb-4eab-8223-f08b85c10f1f",
      "target": "9b3c4c9c-64b0-4937-98e5-bdddb729b882",
      "type": "ClassBidirectional",
      "sourceHandle": "left",
      "targetHandle": "right",
      "data": {
        "label": "contact_company",
        "name": "contact_company",
        "sourceMultiplicity": "0..*",
        "targetMultiplicity": "0..1",
        "sourceRole": "contacts",
        "targetRole": "company",
        "isManuallyLayouted": false,
        "messages": [],
        "points": [
          {
            "x": -270,
            "y": 105
          },
          {
            "x": -590,
            "y": 105
          }
        ]
      }
    },
    {
      "id": "aa73cbaa-d728-43e9-baa3-c486839289ba",
      "source": "fb02ddde-ec4d-4181-bc34-7cabad68eca1",
      "target": "00c036a4-454e-4449-9a9b-6b3f03969d49",
      "type": "ClassBidirectional",
      "sourceHandle": "left-top",
      "targetHandle": "right-bottom",
      "data": {
        "label": "task_opportunity",
        "name": "task_opportunity",
        "sourceMultiplicity": "0..*",
        "targetMultiplicity": "0..1",
        "sourceRole": "tasks",
        "targetRole": "opportunity",
        "isManuallyLayouted": false,
        "messages": [],
        "points": [
          {
            "x": 90,
            "y": 655
          },
          {
            "x": -50,
            "y": 655
          }
        ]
      }
    },
    {
      "id": "16d3b1e0-e666-4c1f-9fdf-9888866aef7a",
      "source": "278327b9-3f33-4fcc-aa98-c144c0933a65",
      "target": "aaddf56f-d3cb-4eab-8223-f08b85c10f1f",
      "type": "ClassBidirectional",
      "sourceHandle": "topleft",
      "targetHandle": "right-bottom",
      "data": {
        "label": "contact_created_by",
        "name": "contact_created_by",
        "sourceMultiplicity": "1..1",
        "targetMultiplicity": "0..*",
        "sourceRole": "created_by",
        "targetRole": "created_contacts",
        "isManuallyLayouted": false,
        "messages": [],
        "points": [
          {
            "x": 445,
            "y": 190
          },
          {
            "x": 445,
            "y": 15
          },
          {
            "x": 70,
            "y": 15
          }
        ]
      }
    },
    {
      "id": "083b5507-d2ed-42a6-85ab-adc5ae11a259",
      "source": "00c036a4-454e-4449-9a9b-6b3f03969d49",
      "target": "278327b9-3f33-4fcc-aa98-c144c0933a65",
      "type": "ClassBidirectional",
      "sourceHandle": "right",
      "targetHandle": "left",
      "data": {
        "label": "opportunity_owner",
        "name": "opportunity_owner",
        "sourceMultiplicity": "0..*",
        "targetMultiplicity": "1..1",
        "sourceRole": "owned_opportunities",
        "targetRole": "owner",
        "isManuallyLayouted": false,
        "messages": [],
        "points": [
          {
            "x": -50,
            "y": 465
          },
          {
            "x": 400,
            "y": 465
          }
        ]
      }
    },
    {
      "id": "268dfa9e-5f38-4600-8b17-19141960af1e",
      "source": "aaddf56f-d3cb-4eab-8223-f08b85c10f1f",
      "target": "ff2a298c-cd09-447f-b868-72d4aa1d34dc",
      "type": "ClassBidirectional",
      "sourceHandle": "left",
      "targetHandle": "right",
      "data": {
        "label": "contact_tag",
        "name": "contact_tag",
        "sourceMultiplicity": "0..*",
        "targetMultiplicity": "0..*",
        "sourceRole": "tagged_contacts",
        "targetRole": "tags",
        "isManuallyLayouted": false,
        "messages": [],
        "points": [
          {
            "x": -270,
            "y": -115
          },
          {
            "x": -600,
            "y": -115
          }
        ]
      }
    },
    {
      "id": "8ba0050a-59c0-4fed-b42b-d3ed579ac2da",
      "source": "2d584aa6-7ca2-4d21-8510-57f70750bfb4",
      "target": "72d64804-891c-438b-bfed-6ecee0bfd085",
      "type": "ClassBidirectional",
      "sourceHandle": "topright",
      "targetHandle": "right-bottom",
      "data": {
        "label": "email_template_link",
        "name": "email_template_link",
        "sourceMultiplicity": "0..1",
        "targetMultiplicity": "0..*",
        "sourceRole": "template",
        "targetRole": "generated_emails",
        "isManuallyLayouted": false,
        "messages": [],
        "points": [
          {
            "x": 945,
            "y": 290
          },
          {
            "x": 945,
            "y": 15
          },
          {
            "x": 820,
            "y": 15
          }
        ]
      }
    },
    {
      "id": "c7db5929-d2f8-41f2-9103-00a640878a74",
      "source": "aaddf56f-d3cb-4eab-8223-f08b85c10f1f",
      "target": "fb02ddde-ec4d-4181-bc34-7cabad68eca1",
      "type": "ClassBidirectional",
      "sourceHandle": "bottomright",
      "targetHandle": "top",
      "data": {
        "label": "task_contact",
        "name": "task_contact",
        "sourceMultiplicity": "0..1",
        "targetMultiplicity": "0..*",
        "sourceRole": "contact",
        "targetRole": "tasks",
        "isManuallyLayouted": false,
        "messages": [],
        "points": [
          {
            "x": -15,
            "y": 130
          },
          {
            "x": -15,
            "y": 335
          },
          {
            "x": 200,
            "y": 335
          },
          {
            "x": 200,
            "y": 540
          }
        ]
      }
    },
    {
      "id": "5da940e4-eca4-4dae-92a6-b27d072c90a7",
      "source": "e2ffed0e-86e2-4ef9-bb83-c7d2f87175a9",
      "target": "aaddf56f-d3cb-4eab-8223-f08b85c10f1f",
      "type": "ClassComposition",
      "sourceHandle": "right",
      "targetHandle": "left-top",
      "data": {
        "label": "score_contact",
        "name": "score_contact",
        "sourceMultiplicity": "0..*",
        "targetMultiplicity": "1..1",
        "sourceRole": "score_history",
        "targetRole": "contact",
        "isManuallyLayouted": false,
        "messages": [],
        "points": [
          {
            "x": -590,
            "y": -285
          },
          {
            "x": -270,
            "y": -285
          }
        ]
      }
    },
    {
      "id": "be60f07b-3f01-4152-b38d-42ae6ec46e14",
      "source": "9b3c4c9c-64b0-4937-98e5-bdddb729b882",
      "target": "00c036a4-454e-4449-9a9b-6b3f03969d49",
      "type": "ClassBidirectional",
      "sourceHandle": "bottom",
      "targetHandle": "left-bottom",
      "data": {
        "label": "opportunity_company",
        "name": "opportunity_company",
        "sourceMultiplicity": "0..1",
        "targetMultiplicity": "0..*",
        "sourceRole": "company",
        "targetRole": "opportunities",
        "isManuallyLayouted": false,
        "messages": [],
        "points": [
          {
            "x": -680,
            "y": 510
          },
          {
            "x": -680,
            "y": 685
          },
          {
            "x": -390,
            "y": 685
          }
        ]
      }
    },
    {
      "id": "6d4d53a2-c678-4b4c-80ce-18cc6fe2943c",
      "source": "72d64804-891c-438b-bfed-6ecee0bfd085",
      "target": "278327b9-3f33-4fcc-aa98-c144c0933a65",
      "type": "ClassBidirectional",
      "sourceHandle": "bottomleft",
      "targetHandle": "right-top",
      "data": {
        "label": "email_user",
        "name": "email_user",
        "sourceMultiplicity": "0..*",
        "targetMultiplicity": "1..1",
        "sourceRole": "generated_emails",
        "targetRole": "created_by",
        "isManuallyLayouted": false,
        "messages": [],
        "points": [
          {
            "x": 685,
            "y": 70
          },
          {
            "x": 685,
            "y": 267.5
          },
          {
            "x": 580,
            "y": 267.5
          }
        ]
      }
    },
    {
      "id": "1deac59c-1c10-4340-af2f-25ed5f90da2b",
      "source": "53490d70-1ecb-4595-89f0-a2309285454e",
      "target": "278327b9-3f33-4fcc-aa98-c144c0933a65",
      "type": "ClassBidirectional",
      "sourceHandle": "right",
      "targetHandle": "topright",
      "data": {
        "label": "interaction_user",
        "name": "interaction_user",
        "sourceMultiplicity": "0..*",
        "targetMultiplicity": "1..1",
        "sourceRole": "interactions",
        "targetRole": "performed_by",
        "isManuallyLayouted": false,
        "messages": [],
        "points": [
          {
            "x": 360,
            "y": -465
          },
          {
            "x": 535,
            "y": -465
          },
          {
            "x": 535,
            "y": 190
          }
        ]
      }
    },
    {
      "id": "a309f5e2-f18f-4acb-b258-395909b31d98",
      "source": "fb02ddde-ec4d-4181-bc34-7cabad68eca1",
      "target": "278327b9-3f33-4fcc-aa98-c144c0933a65",
      "type": "ClassBidirectional",
      "sourceHandle": "right",
      "targetHandle": "bottom",
      "data": {
        "label": "task_user",
        "name": "task_user",
        "sourceMultiplicity": "0..*",
        "targetMultiplicity": "1..1",
        "sourceRole": "tasks",
        "targetRole": "assigned_to",
        "isManuallyLayouted": false,
        "messages": [],
        "points": [
          {
            "x": 310,
            "y": 665
          },
          {
            "x": 490,
            "y": 665
          },
          {
            "x": 490,
            "y": 500
          }
        ]
      }
    },
    {
      "id": "f979f1c8-ed21-4e1d-81d7-d56d8a224065",
      "source": "aaddf56f-d3cb-4eab-8223-f08b85c10f1f",
      "target": "ef128c67-c532-4b67-b248-732b587445a7",
      "type": "ClassBidirectional",
      "sourceHandle": "right-top",
      "targetHandle": "left-top",
      "data": {
        "label": "enrichment_contact",
        "name": "enrichment_contact",
        "sourceMultiplicity": "1..1",
        "targetMultiplicity": "0..*",
        "sourceRole": "contact",
        "targetRole": "enrichment_logs",
        "isManuallyLayouted": false,
        "messages": [],
        "points": [
          {
            "x": 70,
            "y": -185
          },
          {
            "x": 270,
            "y": -185
          }
        ]
      }
    },
    {
      "id": "33ef6d3d-ddd2-450d-b3f7-04c15a0a0f2c",
      "source": "aaddf56f-d3cb-4eab-8223-f08b85c10f1f",
      "target": "00c036a4-454e-4449-9a9b-6b3f03969d49",
      "type": "ClassBidirectional",
      "sourceHandle": "bottomleft",
      "targetHandle": "top",
      "data": {
        "label": "opportunity_contact",
        "name": "opportunity_contact",
        "sourceMultiplicity": "1..*",
        "targetMultiplicity": "0..*",
        "sourceRole": "contacts",
        "targetRole": "opportunities",
        "isManuallyLayouted": false,
        "messages": [],
        "points": [
          {
            "x": -160,
            "y": 130
          },
          {
            "x": -160,
            "y": 430
          }
        ]
      }
    },
    {
      "id": "ece29788-7f1f-4112-af4f-548099abdd6f",
      "source": "aaddf56f-d3cb-4eab-8223-f08b85c10f1f",
      "target": "72d64804-891c-438b-bfed-6ecee0bfd085",
      "type": "ClassBidirectional",
      "sourceHandle": "right-bottom",
      "targetHandle": "left-top",
      "data": {
        "label": "email_contact",
        "name": "email_contact",
        "sourceMultiplicity": "1..1",
        "targetMultiplicity": "0..*",
        "sourceRole": "contact",
        "targetRole": "generated_emails",
        "isManuallyLayouted": false,
        "messages": [],
        "points": [
          {
            "x": 70,
            "y": -40
          },
          {
            "x": 640,
            "y": -40
          }
        ]
      }
    },
    {
      "id": "f21a44ac-7fb2-4497-8646-32e6d98debfb",
      "source": "9b3c4c9c-64b0-4937-98e5-bdddb729b882",
      "target": "278327b9-3f33-4fcc-aa98-c144c0933a65",
      "type": "ClassBidirectional",
      "sourceHandle": "right",
      "targetHandle": "left",
      "data": {
        "label": "company_created_by",
        "name": "company_created_by",
        "sourceMultiplicity": "0..*",
        "targetMultiplicity": "1..1",
        "sourceRole": "created_companies",
        "targetRole": "created_by",
        "isManuallyLayouted": false,
        "messages": [],
        "points": [
          {
            "x": -590,
            "y": 345
          },
          {
            "x": 400,
            "y": 345
          }
        ]
      }
    },
    {
      "id": "5a759dde-93ce-4ddb-9651-0ac0ef9e57ce",
      "source": "53490d70-1ecb-4595-89f0-a2309285454e",
      "target": "aaddf56f-d3cb-4eab-8223-f08b85c10f1f",
      "type": "ClassComposition",
      "sourceHandle": "left",
      "targetHandle": "top",
      "data": {
        "label": "interaction_contact",
        "name": "interaction_contact",
        "sourceMultiplicity": "0..*",
        "targetMultiplicity": "1..1",
        "sourceRole": "interactions",
        "targetRole": "contact",
        "isManuallyLayouted": false,
        "messages": [],
        "points": [
          {
            "x": 110,
            "y": -465
          },
          {
            "x": -100,
            "y": -465
          },
          {
            "x": -100,
            "y": -330
          }
        ]
      }
    },
    {
      "id": "97989673-da1d-4db9-a6e5-8c3c34593baf",
      "source": "9b3c4c9c-64b0-4937-98e5-bdddb729b882",
      "target": "ff2a298c-cd09-447f-b868-72d4aa1d34dc",
      "type": "ClassBidirectional",
      "sourceHandle": "top",
      "targetHandle": "bottom",
      "data": {
        "label": "company_tag",
        "name": "company_tag",
        "sourceMultiplicity": "0..*",
        "targetMultiplicity": "0..*",
        "sourceRole": "tagged_companies",
        "targetRole": "tags",
        "isManuallyLayouted": false,
        "messages": [],
        "points": [
          {
            "x": -685,
            "y": 80
          },
          {
            "x": -685,
            "y": -50
          }
        ]
      }
    }
  ],
  "assessments": {}
}
